phonlab/__init__.py
phonlab/__init__.pyi
phonlab/acoustic/DPPT.py
phonlab/acoustic/amp_env.py
phonlab/acoustic/burst_detect.py
phonlab/acoustic/cepstral.py
phonlab/acoustic/display_wave_.py
phonlab/acoustic/fric_meas.py
phonlab/acoustic/gci.py
phonlab/acoustic/get_HNR.py
phonlab/acoustic/get_f0_.py
phonlab/acoustic/h2h1_.py
phonlab/acoustic/lpc_residual.py
phonlab/acoustic/rhythm.py
phonlab/acoustic/sgram_.py
phonlab/acoustic/shs.py
phonlab/acoustic/tidypraat.py
phonlab/acoustic/track_formants_.py
phonlab/acoustic/vowel_norm.py
phonlab/artic/egg2oq_.py
phonlab/auditory/add_noise_.py
phonlab/auditory/audspec.py
phonlab/auditory/mel_sgram.py
phonlab/auditory/noise_vocoder.py
phonlab/auditory/sigcor.py
phonlab/auditory/sinewave_synth.py
phonlab/data/example_audio/F1_bha24_1.wav
phonlab/data/example_audio/fricatives.wav
phonlab/data/example_audio/im_twelve.TextGrid
phonlab/data/example_audio/im_twelve.wav
phonlab/data/example_audio/might_have_a_class.wav
phonlab/data/example_audio/mono.wav
phonlab/data/example_audio/mono_16bit_integer.wav
phonlab/data/example_audio/mono_32bit_float.wav
phonlab/data/example_audio/sf3_cln.wav
phonlab/data/example_audio/stereo.wav
phonlab/data/example_audio/the_soviet_union.wav
phonlab/data/example_audio/three_plus_five.TextGrid
phonlab/data/example_audio/three_plus_five.wav
phonlab/data/example_audio/threechan.wav
phonlab/data/example_audio/two_plus_two.TextGrid
phonlab/data/example_audio/two_plus_two.wav
phonlab/data/noise/babble.wav
phonlab/data/noise/party.wav
phonlab/data/noise/restaurant.wav
phonlab/third_party/robustsmoothing.py
phonlab/utils/plot_tiers.py
phonlab/utils/prep_audio_.py
phonlab/utils/signal.py
phonlab/utils/tidy.py
phonlab-0.0.47.dist-info/.ipynb_checkpoints/PKG-INFO-checkpoint
phonlab-0.0.47.dist-info/.ipynb_checkpoints/SOURCES-checkpoint.txt
phonlab-0.0.47.dist-info/.ipynb_checkpoints/requires-checkpoint.txt
phonlab-0.0.47.dist-info/.ipynb_checkpoints/top_level-checkpoint.txt
phonlab-0.0.47.dist-info/licenses/LICENSE
phonlab-0.0.47.dist-info/METADATA
phonlab-0.0.47.dist-info/WHEEL
phonlab-0.0.47.dist-info/top_level.txt
phonlab-0.0.47.dist-info/RECORD
