Metadata-Version: 2.4
Name: phonlab
Version: 0.0.47
Summary: Python tools for phonetics
Author-email: Keith Johnson <kjohnson@berkeley.edu>, Ronald Sprouse <rsprouse@berkeley.edu>
License-Expression: BSD-3-Clause
Project-URL: Homepage, https://github.com/phonetics-projects/phonlab
Project-URL: Issues, https://github.com/phonetics-projects/phonlab/issues
Classifier: Programming Language :: Python :: 3
Classifier: Operating System :: OS Independent
Classifier: Intended Audience :: Science/Research
Classifier: Topic :: Scientific/Engineering
Classifier: Topic :: Multimedia :: Sound/Audio :: Speech
Requires-Python: >=3.10
License-File: LICENSE
Requires-Dist: numpy
Requires-Dist: nitime
Requires-Dist: matplotlib
Requires-Dist: scipy
Requires-Dist: srt
Requires-Dist: colorednoise
Requires-Dist: pandas
Requires-Dist: librosa
Requires-Dist: praat-parselmouth
Requires-Dist: scikit-learn
Dynamic: license-file
